{
	"name": "Home",
	"layers": [
		{
			"name": "Layer 0",
			"overriden": 0,
			"subLayers": [],
			"instances": [
				{
					"type": "home_bg",
					"properties": {
						"initially-visible": true,
						"initial-animation": "Default",
						"initial-frame": 0,
						"enable-collisions": true,
						"live-preview": false
					},
					"uid": 2,
					"sid": 723809976321071,
					"tags": "",
					"instanceVariables": {},
					"behaviors": {},
					"instanceFolderItem": {
						"sid": 723809976321071,
						"expanded": true,
						"folderName": "",
						"indexInFolder": -1,
						"folderNestingLevel": -1
					},
					"showing": true,
					"locked": false,
					"world": {
						"x": 429,
						"y": 242.5,
						"width": 862,
						"height": 489.9999999999999,
						"originX": 0.5,
						"originY": 0.5,
						"color": [
							1,
							1,
							1,
							1
						],
						"angle": 0,
						"zElevation": 0
					}
				},
				{
					"type": "play_btn",
					"properties": {
						"initially-visible": true,
						"initial-animation": "Animation 1",
						"initial-frame": 0,
						"enable-collisions": true,
						"live-preview": false
					},
					"uid": 3,
					"sid": 832692173744148,
					"tags": "",
					"instanceVariables": {},
					"behaviors": {},
					"instanceFolderItem": {
						"sid": 832692173744148,
						"expanded": true,
						"folderName": "",
						"indexInFolder": -1,
						"folderNestingLevel": -1
					},
					"showing": true,
					"locked": false,
					"world": {
						"x": 429.8733344038697,
						"y": 308.28813646755856,
						"width": 304.13086784809195,
						"height": 36.783412506400396,
						"originX": 0.5,
						"originY": 0.5,
						"color": [
							1,
							1,
							1,
							1
						],
						"angle": 0,
						"zElevation": 0
					}
				},
				{
					"type": "instruction_btn",
					"properties": {
						"initially-visible": true,
						"initial-animation": "Animation 1",
						"initial-frame": 0,
						"enable-collisions": true,
						"live-preview": false
					},
					"uid": 5,
					"sid": 264961130523856,
					"tags": "",
					"instanceVariables": {},
					"behaviors": {},
					"instanceFolderItem": {
						"sid": 264961130523856,
						"expanded": true,
						"folderName": "",
						"indexInFolder": -1,
						"folderNestingLevel": -1
					},
					"showing": true,
					"locked": false,
					"world": {
						"x": 431.434425580322,
						"y": 356.5098795798489,
						"width": 304.4042554442632,
						"height": 39.269251257257395,
						"originX": 0.5,
						"originY": 0.5,
						"color": [
							1,
							1,
							1,
							1
						],
						"angle": 0,
						"zElevation": 0
					}
				},
				{
					"type": "setting_btn",
					"properties": {
						"initially-visible": true,
						"initial-animation": "Animation 1",
						"initial-frame": 0,
						"enable-collisions": true,
						"live-preview": false
					},
					"uid": 6,
					"sid": 986362473985640,
					"tags": "",
					"instanceVariables": {},
					"behaviors": {},
					"instanceFolderItem": {
						"sid": 986362473985640,
						"expanded": true,
						"folderName": "",
						"indexInFolder": -1,
						"folderNestingLevel": -1
					},
					"showing": true,
					"locked": false,
					"world": {
						"x": 430.51226035205815,
						"y": 403.94852697190595,
						"width": 300.8869661168098,
						"height": 37.716627240929256,
						"originX": 0.5,
						"originY": 0.5,
						"color": [
							1,
							1,
							1,
							1
						],
						"angle": 0,
						"zElevation": 0
					}
				}
			],
			"sid": 462161547164949,
			"effectTypes": [],
			"isInitiallyVisible": true,
			"isInitiallyInteractive": true,
			"isHTMLElementsLayer": false,
			"color": [
				1,
				1,
				1,
				1
			],
			"backgroundColor": [
				1,
				1,
				1,
				1
			],
			"isTransparent": false,
			"parallaxX": 1,
			"parallaxY": 1,
			"scaleRate": 1,
			"forceOwnTexture": false,
			"renderingMode": "3d",
			"drawOrder": "z-order",
			"useRenderCells": false,
			"blendMode": "normal",
			"zElevation": 0,
			"global": false
		}
	],
	"scene-graphs-folder-root": {
		"items": [],
		"subfolders": []
	},
	"sid": 694525356076102,
	"nonworld-instances": [],
	"effectTypes": [],
	"width": 1708,
	"height": 960,
	"unboundedScrolling": false,
	"vpX": 0.5,
	"vpY": 0.5,
	"projection": "perspective",
	"eventSheet": "Home"
}